s3dgraphy/__init__.py
s3dgraphy/graph.py
s3dgraphy/indices.py
s3dgraphy/JSON_config/em_cidoc_mapping.json
s3dgraphy/JSON_config/em_document_types.json
s3dgraphy/JSON_config/em_extractor_types.json
s3dgraphy/JSON_config/em_qualia_types.json
s3dgraphy/JSON_config/em_visual_rules.json
s3dgraphy/JSON_config/s3Dgraphy_connections_datamodel.json
s3dgraphy/JSON_config/s3Dgraphy_node_datamodel .json
s3dgraphy/JSON_config/s3dgraphy.ttl
s3dgraphy/JSON_config/s3dgraphy_nomapping.ttl
s3dgraphy/JSON_config/src/2D/SF.png
s3dgraphy/JSON_config/src/2D/TSU.png
s3dgraphy/JSON_config/src/2D/US.png
s3dgraphy/JSON_config/src/2D/USD.png
s3dgraphy/JSON_config/src/2D/USVn.png
s3dgraphy/JSON_config/src/2D/USVs.png
s3dgraphy/JSON_config/src/2D/VSF.png
s3dgraphy/JSON_config/src/2D/combiner.png
s3dgraphy/JSON_config/src/2D/continuity.png
s3dgraphy/JSON_config/src/2D/document.png
s3dgraphy/JSON_config/src/2D/extractor.png
s3dgraphy/JSON_config/src/2D/property.png
s3dgraphy/JSON_config/src/2D/serSU.png
s3dgraphy/JSON_config/src/2D/serUSV.png
s3dgraphy/JSON_config/src/3D/SF.glb
s3dgraphy/JSON_config/src/3D/TSU.glb
s3dgraphy/JSON_config/src/3D/US.glb
s3dgraphy/JSON_config/src/3D/USD.glb
s3dgraphy/JSON_config/src/3D/USVn.glb
s3dgraphy/JSON_config/src/3D/USVs.glb
s3dgraphy/JSON_config/src/3D/VSF.glb
s3dgraphy/JSON_config/src/3D/combiner.glb
s3dgraphy/JSON_config/src/3D/continuity.glb
s3dgraphy/JSON_config/src/3D/document.glb
s3dgraphy/JSON_config/src/3D/extractor.glb
s3dgraphy/JSON_config/src/3D/property.glb
s3dgraphy/JSON_config/src/3D/serSU.glb
s3dgraphy/JSON_config/src/3D/serUSV.glb
s3dgraphy/edges/__init__.py
s3dgraphy/edges/connections_loader.py
s3dgraphy/edges/edge.py
s3dgraphy/exporter/__init__.py
s3dgraphy/exporter/json_exporter.py
s3dgraphy/importer/__init__.py
s3dgraphy/importer/base_importer.py
s3dgraphy/importer/import_graphml.py
s3dgraphy/importer/mapped_xlsx_importer.py
s3dgraphy/importer/pyarchinit_importer.py
s3dgraphy/importer/xlsx_importer.py
s3dgraphy/mappings/__init__.py
s3dgraphy-0.1.25.dist-info/licenses/LICENSE
s3dgraphy-0.1.25.dist-info/METADATA
s3dgraphy-0.1.25.dist-info/WHEEL
s3dgraphy-0.1.25.dist-info/top_level.txt
s3dgraphy-0.1.25.dist-info/RECORD
