Metadata-Version: 2.4
Name: s3dgraphy
Version: 0.1.25
Summary: 3D Stratigraphic Graph Management Library for archaeological and heritage applications
Author-email: Emanuel Demetrescu <emanuel.demetrescu@cnr.it>
Maintainer-email: Emanuel Demetrescu <emanuel.demetrescu@cnr.it>
License: GPL-3.0-or-later
Project-URL: Homepage, https://github.com/zalmoxes-laran/s3dgraphy
Project-URL: Documentation, https://docs.extendedmatrix.org/projects/s3dgraphy/
Project-URL: Repository, https://github.com/zalmoxes-laran/s3dgraphy.git
Project-URL: Bug Reports, https://github.com/zalmoxes-laran/s3dgraphy/issues
Project-URL: Source Code, https://github.com/zalmoxes-laran/s3dgraphy
Project-URL: Extended Matrix, https://www.extendedmatrix.org
Project-URL: Changelog, https://github.com/zalmoxes-laran/s3dgraphy/blob/main/CHANGELOG.md
Keywords: archaeology,stratigraphy,graph,3d,heritage,temporal-modeling,knowledge-graph,extended-matrix
Classifier: Development Status :: 4 - Beta
Classifier: Intended Audience :: Science/Research
Classifier: Intended Audience :: Education
Classifier: Topic :: Scientific/Engineering :: Information Analysis
Classifier: Topic :: Scientific/Engineering :: Visualization
Classifier: Topic :: Database :: Database Engines/Servers
Classifier: License :: OSI Approved :: GNU General Public License v3 or later (GPLv3+)
Classifier: Programming Language :: Python :: 3
Classifier: Programming Language :: Python :: 3.8
Classifier: Programming Language :: Python :: 3.9
Classifier: Programming Language :: Python :: 3.10
Classifier: Programming Language :: Python :: 3.11
Classifier: Programming Language :: Python :: 3.12
Classifier: Operating System :: OS Independent
Classifier: Environment :: Console
Classifier: Natural Language :: English
Requires-Python: >=3.8
License-File: LICENSE
Requires-Dist: pandas>=2.0.0
Requires-Dist: numpy>=1.21.0
Provides-Extra: dev
Requires-Dist: pytest>=7.0; extra == "dev"
Requires-Dist: pytest-cov; extra == "dev"
Requires-Dist: black; extra == "dev"
Requires-Dist: flake8; extra == "dev"
Requires-Dist: mypy; extra == "dev"
Requires-Dist: build; extra == "dev"
Requires-Dist: twine; extra == "dev"
Requires-Dist: bump2version; extra == "dev"
Provides-Extra: docs
Requires-Dist: sphinx>=5.0; extra == "docs"
Requires-Dist: sphinx-rtd-theme; extra == "docs"
Requires-Dist: myst-parser; extra == "docs"
Provides-Extra: visualization
Requires-Dist: networkx>=3.0; extra == "visualization"
Requires-Dist: matplotlib>=3.0; extra == "visualization"
Requires-Dist: plotly>=5.0; extra == "visualization"
Provides-Extra: full
Requires-Dist: s3dgraphy[dev,docs,visualization]; extra == "full"
Dynamic: license-file
